openapi_client/__init__.py
openapi_client/api_client.py
openapi_client/api_response.py
openapi_client/configuration.py
openapi_client/exceptions.py
openapi_client/py.typed
openapi_client/rest.py
openapi_client/api/__init__.py
openapi_client/api/default_api.py
openapi_client/models/__init__.py
openapi_client/models/http_validation_error.py
openapi_client/models/validation_error.py
openapi_client/models/validation_error_loc_inner.py
orion_ai_sdk-1.0.0.dist-info/LICENSE
orion_ai_sdk-1.0.0.dist-info/METADATA
orion_ai_sdk-1.0.0.dist-info/WHEEL
orion_ai_sdk-1.0.0.dist-info/top_level.txt
orion_ai_sdk-1.0.0.dist-info/RECORD
